{"882":[{"duration":"1516.17","number":1,"title":"Episode 1"}],"1713":[{"duration":"1476.79","number":1,"title":"A Deep Sea Explorer Disappeared!"},{"duration":"1479.33","number":2,"title":"Scramble, the Super Submarine!"},{"duration":"1478.21","number":3,"title":"Battle at 39600 Feet Deep!"},{"duration":"1478.88","number":4,"title":"The Ambush Achieved Great Success!"},{"duration":"1477.88","number":5,"title":"Challenge of A Young Warrior"},{"duration":"1477.83","number":6,"title":"Hold-Up"},{"duration":"1478.75","number":7,"title":"A Booby Trap!"},{"duration":"1479.21","number":8,"title":"Coronation of Emperor Is Declared!"},{"duration":"1477.46","number":9,"title":"Decision of A Great General"},{"duration":"1479.00","number":10,"title":"Blast the Ocean Empire!"},{"duration":"1478.71","number":11,"title":"Farewell, the Great General!"},{"duration":"1478.54","number":12,"title":"Decisive Battle"},{"duration":"1461.04","number":13,"title":"Embark to A New Ocean!"}],"10058":[{"duration":"3363.13","number":1,"title":"Episode 1"}],"32740":[{"duration":"958.04","intro":[0,88],"outro":[867,948],"number":1,"title":"Episode 1"}],"38137":[{"duration":"5424.21","number":1,"title":"Episode 1"}],"42044":[{"duration":"440.83","number":1,"title":"Episode 1"}],"45169":[{"duration":"1385.58","number":1,"title":"Episode 1"},{"duration":"1316.67","number":2,"title":"Episode 2"},{"duration":"1298.17","number":3,"title":"Episode 3"},{"duration":"1235.79","number":4,"title":"Episode 4"},{"duration":"1351.75","number":5,"title":"Episode 5"},{"duration":"1264.29","number":6,"title":"Episode 6"},{"duration":"1139.79","number":7,"title":"Episode 7"},{"duration":"1007.13","number":8,"title":"Episode 8"},{"duration":"1175.33","number":9,"title":"Episode 9"},{"duration":"1062.08","number":10,"title":"Episode 10"},{"duration":"1133.46","number":11,"title":"Episode 11"},{"duration":"838.33","number":12,"title":"Episode 12"},{"duration":"952.71","number":13,"title":"Episode 13"}],"48406":[{"duration":"1393.92","intro":[106,192],"outro":[1390,1393],"number":1,"title":"Sorry, Who Are You?"},{"duration":"1406.08","intro":[206,295],"outro":[1370,1406],"number":2,"title":"I`m No Prodigy"},{"duration":"1406.08","intro":[183,272],"outro":[1320,1406],"number":3,"title":"But, Give Us a Hendy"},{"duration":"1406.00","intro":[346,435],"outro":[1317,1395],"number":4,"title":"This Ain`t Looking Good..."},{"duration":"1402.08","intro":[190,280],"outro":[1350,1402],"number":5,"title":"Dude, That`s Scary!!!"},{"duration":"1402.08","intro":[164,253],"outro":[1312,1402],"number":6,"title":"Hey! Look This Way!"},{"duration":"1402.00","intro":[224,314],"number":7,"title":"Auspicious Day"},{"duration":"1402.00","intro":[333,425],"number":8,"title":"Who Are These Guys?"},{"duration":"1402.04","number":9,"title":"I`ve Always Been Me"},{"duration":"1387.13","number":10,"title":"It`s the Only Way I Know to Win"},{"duration":"1391.04","number":11,"title":"Pass! Pass to Me!"},{"duration":"1390.96","number":12,"title":"C`mon, Let`s Get Started"}],"48612":[{"duration":"6589.38","number":1,"title":"Episode 1"}],"48753":[{"duration":"1419.08","intro":[0,83],"number":1,"title":"The Great Jahy Can`t Go Back!"},{"duration":"1419.17","intro":[85,173],"outro":[1324,1418],"number":2,"title":"Druj Asks No Questions!"},{"duration":"1419.13","intro":[54,144],"outro":[1146,1405],"number":3,"title":"The Great Jahy Can`t Brag..."},{"duration":"1419.08","intro":[38,128],"outro":[1192,1281],"number":4,"title":"Saurva Never Slips Up?"},{"duration":"1419.04","intro":[60,150],"outro":[1113,1203],"number":5,"title":"The Great Jahy Isn`t Suspicious?!"},{"duration":"1419.17","intro":[28,118],"outro":[1147,1237],"number":6,"title":"The Great Jahy Doesn`t Seem to Stand a Chance..."},{"duration":"1419.08","intro":[40,130],"outro":[1277,1366],"number":7,"title":"The Great Jahy Doesn`t Play!"},{"duration":"1419.13","intro":[30,120],"outro":[1325,1419],"number":8,"title":"The Great Jahy Can`t Bathe!"},{"duration":"1419.13","intro":[45,135],"outro":[1325,1419],"number":9,"title":"Saurva Can`t Catch a Break..."},{"duration":"1419.08","intro":[45,135],"outro":[1250,1340],"number":10,"title":"The Magical Girl Will Not Lose!"},{"duration":"1419.04","intro":[70,160],"outro":[1325,1419],"number":11,"title":"The Landlord Can`t Come Home..."},{"duration":"1404.08","intro":[15,105],"outro":[1170,1260],"number":12,"title":"Kokoro-chan Will Not Betray?"},{"duration":"1404.08","intro":[60,150],"outro":[1255,1345],"number":13,"title":"Druj Is Not Happy!"},{"duration":"1404.13","intro":[30,120],"outro":[1310,1404],"number":14,"title":"The Magical Girl Will Not Fight!"},{"duration":"1404.04","intro":[0,90],"outro":[1310,1404],"number":15,"title":"The Boss Cannot Decide!"},{"duration":"1404.08","intro":[46,135],"outro":[1309,1399],"number":16,"title":"The Dark Lord Doesn`t Hold Back!"},{"duration":"1404.13","intro":[55,145],"outro":[1070,1160],"number":17,"title":"The Great Jahy Can`t Sleep..."},{"duration":"1404.13","intro":[60,150],"outro":[1310,1404],"number":18,"title":"Saurva Will Not Lose!"},{"duration":"1404.04","intro":[15,105],"outro":[1310,1404],"number":19,"title":"The Demon Lord Is Relentless?!"},{"duration":"1404.13","number":20,"title":"The Great Jahy Will Not Be Defeated!"}]}