{"2706":[{"duration":"1407.08","number":1},{"duration":"1406.00","number":2},{"duration":"1406.17","number":3},{"duration":"1406.13","number":4},{"duration":"1406.04","number":5},{"duration":"1406.13","number":6},{"duration":"1407.08","number":7},{"duration":"1406.08","number":8},{"duration":"1406.13","number":9},{"duration":"1406.13","number":10},{"duration":"1406.13","number":11},{"duration":"1406.04","number":12},{"duration":"1407.08","number":13},{"duration":"1406.13","number":14},{"duration":"1406.00","number":15},{"duration":"1406.08","number":16},{"duration":"1406.13","number":17},{"duration":"1406.08","number":18},{"duration":"1407.04","number":19},{"duration":"1406.08","number":20},{"duration":"1406.13","number":21},{"duration":"1406.08","number":22},{"duration":"1406.04","number":23},{"duration":"1406.13","number":24},{"duration":"1406.29","number":25},{"duration":"1406.25","number":26},{"duration":"1406.29","number":27},{"duration":"1406.08","number":28},{"duration":"1406.00","number":29},{"duration":"1406.04","number":30},{"duration":"1407.50","number":31},{"duration":"1406.04","number":32},{"duration":"1406.08","number":33},{"duration":"1406.17","number":34},{"duration":"1406.08","number":35},{"duration":"1406.13","number":36},{"duration":"1407.08","number":37},{"duration":"1406.00","number":38},{"duration":"1406.08","number":39},{"duration":"1501.71","number":40},{"duration":"1406.04","number":41},{"duration":"1406.04","number":42},{"duration":"1407.13","number":43},{"duration":"1406.17","number":44},{"duration":"1406.08","number":45}],"4574":[{"duration":"1479.92","number":1},{"duration":"1478.96","number":2},{"duration":"1478.96","number":3},{"duration":"1478.96","number":4},{"duration":"1478.88","number":5},{"duration":"1478.88","number":6},{"duration":"1479.92","number":7},{"duration":"1478.88","number":8},{"duration":"1479.92","number":9},{"duration":"1479.92","number":10},{"duration":"1478.88","number":11},{"duration":"1501.92","number":12},{"duration":"1479.92","number":13},{"duration":"1479.92","number":14},{"duration":"1478.38","number":15},{"duration":"1479.42","number":16},{"duration":"1478.29","number":17},{"duration":"1501.42","number":18},{"duration":"1479.92","number":19},{"duration":"1480.33","number":20},{"duration":"1480.42","number":21},{"duration":"1479.42","number":22},{"duration":"1478.88","number":23},{"duration":"1502.33","number":24},{"duration":"1478.88","number":25},{"duration":"1478.88","number":26},{"duration":"1478.88","number":27},{"duration":"1478.38","number":28},{"duration":"1478.88","number":29},{"duration":"1501.79","number":30},{"duration":"1479.92","number":31},{"duration":"1479.92","number":32},{"duration":"1479.92","number":33},{"duration":"1478.88","number":34},{"duration":"1480.33","number":35},{"duration":"1502.08","number":36},{"duration":"1479.92","number":37},{"duration":"1479.42","number":38},{"duration":"1478.88","number":39},{"duration":"1480.33","number":40},{"duration":"1479.92","number":41},{"duration":"1502.25","number":42},{"duration":"1479.92","number":43},{"duration":"1479.33","number":44},{"duration":"1480.33","number":45},{"duration":"1479.42","number":46},{"duration":"1479.92","number":47},{"duration":"1502.29","number":48},{"duration":"1479.92","number":49},{"duration":"1472.25","number":50}],"16303":[{"duration":"1419.25","number":1,"title":"Episode 1"},{"duration":"1419.25","number":2,"title":"Episode 2"},{"duration":"1418.25","number":3,"title":"Episode 3"},{"duration":"1418.25","number":4,"title":"Episode 4"},{"duration":"1418.46","number":5,"title":"Episode 5"},{"duration":"1418.63","number":6,"title":"Episode 6"},{"duration":"1417.96","number":7,"title":"Episode 7"},{"duration":"1418.71","number":8,"title":"Episode 8"},{"duration":"1418.13","number":9,"title":"Episode 9"},{"duration":"1418.79","number":10,"title":"Episode 10"},{"duration":"1417.29","number":11,"title":"Episode 11"},{"duration":"1418.25","number":12,"title":"Episode 12"},{"duration":"1418.79","number":13,"title":"Episode 13"},{"duration":"1418.29","number":14,"title":"Episode 14"}],"18617":[{"duration":"7211.33","number":1,"title":"Episode 1"}],"28057":[{"duration":"579.88","number":1,"title":"Episode 1"}],"38467":[{"duration":"1019.92","number":1},{"duration":"1015.25","intro":[24,149],"outro":[827,1015],"number":2},{"duration":"1023.88","intro":[26,148],"outro":[831,1020],"number":3},{"duration":"1045.25","intro":[0,155],"outro":[848,1045],"number":4},{"duration":"1040.92","intro":[4,209],"outro":[890,1035],"number":5},{"duration":"998.33","intro":[2,207],"outro":[850,998],"number":6},{"duration":"1038.21","intro":[20,206],"outro":[902,1002],"number":7},{"duration":"967.17","number":8},{"duration":"1004.92","intro":[5,210],"outro":[829,1002],"number":9},{"duration":"1009.63","intro":[3,202],"outro":[835,1009],"number":10},{"duration":"1015.83","intro":[3,203],"outro":[838,1015],"number":11},{"duration":"1005.67","number":12},{"duration":"982.21","number":13},{"duration":"983.54","intro":[20,205],"outro":[853,960],"number":14},{"duration":"975.79","intro":[21,200],"outro":[845,945],"number":15},{"duration":"961.79","number":16},{"duration":"968.83","number":17},{"duration":"973.08","intro":[1,156],"number":18},{"duration":"968.17","intro":[0,215],"number":19},{"duration":"1039.04","intro":[2,212],"number":20},{"duration":"985.25","number":21},{"duration":"992.67","intro":[0,208],"number":22},{"duration":"986.17","number":23},{"duration":"981.83","number":24},{"duration":"982.83","number":25},{"duration":"970.79","number":26},{"duration":"1124.63","number":27},{"duration":"965.25","number":28},{"duration":"959.21","number":29},{"duration":"978.21","number":30},{"duration":"975.42","number":31},{"duration":"980.25","number":32},{"duration":"991.83","number":33},{"duration":"985.83","number":34},{"duration":"985.29","number":35},{"duration":"1016.58","number":36},{"duration":"1029.88","number":37},{"duration":"993.71","number":38},{"duration":"1000.75","number":39},{"duration":"985.13","number":40},{"duration":"1100.33","number":41},{"duration":"1166.46","number":42}],"38939":[{"duration":"103.17","number":1,"title":"Episode 1"},{"duration":"182.25","number":2,"title":"Episode 2"},{"duration":"172.92","number":3,"title":"Episode 3"}],"38981":[{"duration":"205.29","number":1,"title":"Episode 1"}],"38992":[{"duration":"1419.67","intro":[166,255],"outro":[1300,1390],"number":1,"title":"Science-types Fell in Love, So They Tried to Analyze It."},{"duration":"1420.04","intro":[99,188],"outro":[1324,1415],"number":2,"title":"Science-types Fell in Love, So They Tried Experiments."},{"duration":"1420.08","intro":[1,89],"outro":[1324,1420],"number":3,"title":"Science-types Fell in Love, So They Try Planning a Date."},{"duration":"1420.13","intro":[68,158],"outro":[1325,1415],"number":4,"title":"Science-types Fell in Love, So They Tried Going On a Date."},{"duration":"1420.08","intro":[98,187],"outro":[1325,1414],"number":5,"title":"Science-types Fell in Love, So They Tried Holding a Meeting."},{"duration":"1420.08","intro":[1,89],"outro":[1287,1376],"number":6,"title":"Science-types Fell in Love, So They Tried Kissing."},{"duration":"1420.75","intro":[43,132],"outro":[1181,1270],"number":7,"title":"Science-types Fell in Love, So They Tried Having a Drinking Party."},{"duration":"1420.08","intro":[0,88],"outro":[1325,1415],"number":8,"title":"Science-types Fell in Love, So They Tried to Gather Evidence of Love."},{"duration":"1420.13","intro":[60,150],"outro":[1239,1328],"number":9,"title":"Science-types Fell in Love, So They Tried Attending a Training Camp in Okinawa."},{"duration":"1420.08","intro":[1,87],"outro":[1325,1414],"number":10,"title":"Science-types Fell in Love, So They Tried Giving Presentations."},{"duration":"1420.08","intro":[1,87],"outro":[1325,1414],"number":11,"title":"Science-types Fell in Love, So They Tried Having a Fight."},{"duration":"1420.13","number":12,"title":"I Knew I Could Fall in Love with You, So I Tried to Prove It."}]}